sputnikqa/__init__.py
sputnikqa/boosters/__init__.py
sputnikqa/boosters/restapi/__init__.py
sputnikqa/boosters/restapi/clients/__init__.py
sputnikqa/boosters/restapi/clients/api_client.py
sputnikqa/boosters/restapi/clients/base.py
sputnikqa/boosters/restapi/clients/httpx_client.py
sputnikqa/boosters/restapi/middleware/__init__.py
sputnikqa/boosters/restapi/middleware/base.py
sputnikqa/boosters/restapi/mixins/__init__.py
sputnikqa/boosters/restapi/mixins/curl.py
sputnikqa/boosters/restapi/request_builders.py
sputnikqa/boosters/restapi/response_models.py
sputnikqa/boosters/restapi/sections/__init__.py
sputnikqa/boosters/restapi/sections/base.py
sputnikqa/boosters/restapi/types.py
sputnikqa/boosters/restapi/utils/openapi_examples/adverts_internal.json
sputnikqa/boosters/restapi/utils/openapi_examples/adverts_public.json
sputnikqa/boosters/restapi/utils/openapi_examples/atomverse.json
sputnikqa/boosters/restapi/utils/openapi_examples/payments_internal.json
sputnikqa/boosters/restapi/utils/openapi_examples/petstore.json
sputnikqa/boosters/restapi/utils/openapi_gen/aaa.py
sputnikqa/boosters/restapi/utils/openapi_gen/parameters.txt
sputnikqa/boosters/restapi/utils/openapi_gen/request_bodies.txt
sputnikqa/boosters/restapi/validators/__init__.py
sputnikqa/boosters/restapi/validators/base.py
sputnikqa/integrations/__init__.py
sputnikqa/integrations/allure/__init__.py
sputnikqa/integrations/allure/client.py
sputnikqa/integrations/allure/middleware.py
sputnikqa-0.0.2a3.dist-info/LICENSE
sputnikqa-0.0.2a3.dist-info/METADATA
sputnikqa-0.0.2a3.dist-info/WHEEL
sputnikqa-0.0.2a3.dist-info/RECORD
