Metadata-Version: 2.1
Name: sputnikqa
Version: 0.0.2a3
Summary: Extensible test automation framework — built for QA engineers who value clean architecture and scalability.
License: MIT
Author: Crenom
Author-email: pytimdev@mail.ru
Requires-Python: >=3.13,<4.0
Classifier: License :: OSI Approved :: MIT License
Classifier: Programming Language :: Python :: 3
Provides-Extra: allure
Requires-Dist: allure-python-commons (>=2.15.0,<3.0.0) ; extra == "allure"
Requires-Dist: httpx (>=0.28.1,<0.29.0)
Requires-Dist: pydantic (>=2.11.9,<3.0.0)
